{
    "questionary_name": "Video Games questionary",
    "image_url": "https://media.istockphoto.com/id/1334436084/photo/top-down-view-of-colorful-illuminated-gaming-accessories-laying-on-table.jpg?s=612x612&w=0&k=20&c=E9xnbAZoBS5LlUX0q-zxT_3m6gEZpyB2k51_U4LLMNs=",
    "questions":[
        {
            "type":"DICHOTOMIC",
            "id":0,
            "text": "DO YOU LIKE VIDEO GAMES",
            "options":["YES","NO"],
            "next":[0,-1]
        },        
        {
            "type":"TEXT",
            "id":1,
            "text": "What is your favourite video game?",
            "options":["Paris","New York"],
            "next":2
        },        
        {
            "type":"MULTIPLECHOICE",
            "id":2,
            "text": "What video game do you like ?",
            "options":["GTA","FORZA","ROCKET LEAGUE","CALL OF DUTY"],
            "next":3
        },
        {
            "type":"DRAG_N_DROP_LIST",
            "id":3,
            "text": "Classez ces options",
            "options":["GTA","FORZA","ROCKET LEAGUE","CALL OF DUTY","Metroid","Bombeirb"],
            "next": 4
        },
        {
            "type":"STAR_RATING",
            "id":4,
            "text": "How would you rate this quizz?",
            "range":[0,3,5],
            "next":-1
        }
    ]
}